keeper_secrets_manager_storage_oracle_kms/__init__.py
keeper_secrets_manager_storage_oracle_kms/constants.py
keeper_secrets_manager_storage_oracle_kms/oci_kms_client.py
keeper_secrets_manager_storage_oracle_kms/oci_session_config.py
keeper_secrets_manager_storage_oracle_kms/oracle_key_value_storage.py
keeper_secrets_manager_storage_oracle_kms/utils.py
keeper_secrets_manager_storage_oracle_kms-1.0.0.dist-info/licenses/LICENSE
keeper_secrets_manager_storage_oracle_kms-1.0.0.dist-info/METADATA
keeper_secrets_manager_storage_oracle_kms-1.0.0.dist-info/WHEEL
keeper_secrets_manager_storage_oracle_kms-1.0.0.dist-info/top_level.txt
keeper_secrets_manager_storage_oracle_kms-1.0.0.dist-info/RECORD
